pdfparser/__init__.py
pdfparser/poppler.cpython-37m-darwin.so
pdfparser/poppler.pyx
pdfparser_si-0.2.6.dist-info/LICENSE
pdfparser_si-0.2.6.dist-info/METADATA
pdfparser_si-0.2.6.dist-info/WHEEL
pdfparser_si-0.2.6.dist-info/top_level.txt
pdfparser_si-0.2.6.dist-info/RECORD
