Metadata-Version: 2.1
Name: pdfparser-si
Version: 0.2.6
Summary: python bindings for poppler
Home-page: https://github.com/minhdang900/pdfparser-si
Author: UNKNOWN
Author-email: UNKNOWN
License: UNKNOWN
Keywords: poppler pdf parsing mining extracting
Platform: UNKNOWN
Classifier: Development Status :: 4 - Beta
Classifier: Intended Audience :: Developers
Classifier: Topic :: Software Development :: Libraries :: Python Modules
Classifier: License :: OSI Approved :: Apple Public Source License
Classifier: Programming Language :: Python :: 2.7
Classifier: Programming Language :: Python :: 3.5
Classifier: Programming Language :: Python :: 3.6
Requires-Dist: cython
